anacostia_pipeline/__init__.py
anacostia_pipeline/nodes/__init__.py
anacostia_pipeline/nodes/api.py
anacostia_pipeline/nodes/connector.py
anacostia_pipeline/nodes/gui.py
anacostia_pipeline/nodes/node.py
anacostia_pipeline/nodes/utils.py
anacostia_pipeline/nodes/actions/__init__.py
anacostia_pipeline/nodes/actions/node.py
anacostia_pipeline/nodes/metadata/__init__.py
anacostia_pipeline/nodes/metadata/api.py
anacostia_pipeline/nodes/metadata/node.py
anacostia_pipeline/nodes/metadata/sql/__init__.py
anacostia_pipeline/nodes/metadata/sql/api.py
anacostia_pipeline/nodes/metadata/sql/fragments.py
anacostia_pipeline/nodes/metadata/sql/gui.py
anacostia_pipeline/nodes/metadata/sql/models.py
anacostia_pipeline/nodes/metadata/sql/node.py
anacostia_pipeline/nodes/metadata/sql/sqlite/__init__.py
anacostia_pipeline/nodes/metadata/sql/sqlite/node.py
anacostia_pipeline/nodes/resources/__init__.py
anacostia_pipeline/nodes/resources/api.py
anacostia_pipeline/nodes/resources/node.py
anacostia_pipeline/nodes/resources/filesystem/__init__.py
anacostia_pipeline/nodes/resources/filesystem/api.py
anacostia_pipeline/nodes/resources/filesystem/fragments.py
anacostia_pipeline/nodes/resources/filesystem/gui.py
anacostia_pipeline/nodes/resources/filesystem/node.py
anacostia_pipeline/nodes/resources/filesystem/utils.py
anacostia_pipeline/nodes/resources/filesystem/croissant/__init__.py
anacostia_pipeline/nodes/resources/filesystem/croissant/fragments.py
anacostia_pipeline/nodes/resources/filesystem/croissant/gui.py
anacostia_pipeline/nodes/resources/filesystem/croissant/node.py
anacostia_pipeline/nodes/resources/filesystem/hugging_face/__init__.py
anacostia_pipeline/nodes/resources/filesystem/hugging_face/repocard.py
anacostia_pipeline/nodes/resources/filesystem/hugging_face/repocard_data.py
anacostia_pipeline/nodes/resources/filesystem/hugging_face/utils.py
anacostia_pipeline/nodes/resources/filesystem/hugging_face/dataset_registry/__init__.py
anacostia_pipeline-0.8.9.dist-info/licenses/LICENSE
anacostia_pipeline-0.8.9.dist-info/METADATA
anacostia_pipeline-0.8.9.dist-info/WHEEL
anacostia_pipeline-0.8.9.dist-info/top_level.txt
anacostia_pipeline-0.8.9.dist-info/RECORD
