Metadata-Version: 2.4
Name: anacostia_pipeline
Version: 0.8.9
Summary: A framework for building MLOps pipelines
Author: Minh-Quan Do
Author-email: mdo9@gmu.edu
License-File: LICENSE
Requires-Dist: sqlalchemy>=1.4.0
Requires-Dist: networkx==3.1
Requires-Dist: markdown
Requires-Dist: jinja2>=3.0.0
Requires-Dist: pydantic
Requires-Dist: fastapi
Requires-Dist: uvicorn[standard]
Requires-Dist: httpx
Provides-Extra: aws
Requires-Dist: boto3; extra == "aws"
Dynamic: author
Dynamic: author-email
Dynamic: description
Dynamic: description-content-type
Dynamic: license-file
Dynamic: provides-extra
Dynamic: requires-dist
Dynamic: summary
